agricore_sp_models/__init__.py
agricore_sp_models/abm_interface.py
agricore_sp_models/agricore_sp_models.py
agricore_sp_models/common_models.py
agricore_sp_models/import_models.py
agricore_sp_models/logging.py
agricore_sp_models/product_market_models.py
agricore_sp_models/py.typed
agricore_sp_models/simulation_models.py
agricore_sp_models-0.5.85.dist-info/METADATA
agricore_sp_models-0.5.85.dist-info/WHEEL
agricore_sp_models-0.5.85.dist-info/RECORD
