Metadata-Version: 2.1
Name: agricore_sp_models
Version: 0.5.85
Summary: 
Home-page: https://github.com/idener/AGRICORE-synthetic-population-models
Author: Antonio Gomez
Author-email: antonio.gomez@idener.es
Requires-Python: >=3.8,<4.0
Classifier: Programming Language :: Python :: 3
Classifier: Programming Language :: Python :: 3.8
Classifier: Programming Language :: Python :: 3.9
Classifier: Programming Language :: Python :: 3.10
Classifier: Programming Language :: Python :: 3.11
Classifier: Programming Language :: Python :: 3.12
Requires-Dist: pydantic (>=1.10.9,<2)
Requires-Dist: requests (>=2.31.0,<3.0.0)
Project-URL: Repository, https://github.com/idener/AGRICORE-synthetic-population-models
